{"id":1148343,"retrievedAt":"2025-04-26T01:49:08.937Z","response":{"adult":false,"backdrop_path":"/wyaBqurezQubtip2D7VfBFbsmtT.jpg","belongs_to_collection":null,"budget":10000,"genres":[{"id":10402,"name":"Music"},{"id":35,"name":"Comedy"}],"homepage":"https://linktr.ee/sweetrhythm","id":1148343,"imdb_id":"tt26083656","origin_country":["AU"],"original_language":"en","original_title":"Sweet Rhythm","overview":"Jennifer, a young Jazz enthusiast, is struggling to embrace her love for music while trying to win her mothers approval when she meets the rebellious hippie Stephanie, and the Rock'n'Roll musician Dani, who flip her world inside out and take her on a disco groovin', rockin' rollin' and jazz swinging adventure across the 70s to save the family diner.","popularity":0.1906,"poster_path":"/yk6eMTwSdSb4TKEUmEPF6xvfnKt.jpg","production_companies":[{"id":168734,"logo_path":null,"name":"Outatime Pictures","origin_country":""}],"production_countries":[{"iso_3166_1":"AU","name":"Australia"}],"release_date":"2023-06-11","revenue":0,"runtime":116,"spoken_languages":[],"status":"Released","tagline":"Sweet Rhythm is a 1977 Rock N' Roll, Jazz and Disco inspired musical that follows Jennifer, Dani and Stephanie as they experience the thrills of being in their 20s.","title":"Sweet Rhythm","video":false,"vote_average":9,"vote_count":1,"alternative_titles":{"titles":[]},"credits":{"cast":[{"adult":false,"gender":0,"id":4148225,"known_for_department":"Acting","name":"Prudence Ackrill","original_name":"Prudence Ackrill","popularity":0.0143,"profile_path":null,"cast_id":11,"character":"Jennifer","credit_id":"64a5871b158c8500acb43b4a","order":0},{"adult":false,"gender":0,"id":4148226,"known_for_department":"Acting","name":"Lainey O'Sullivan","original_name":"Lainey O'Sullivan","popularity":0.0214,"profile_path":null,"cast_id":12,"character":"Dani","credit_id":"64a587265a991501007d99f5","order":1},{"adult":false,"gender":0,"id":4148227,"known_for_department":"Acting","name":"Hannah Julii Anderson","original_name":"Hannah Julii Anderson","popularity":0,"profile_path":null,"cast_id":13,"character":"Stephanie","credit_id":"64a587328c44b900ae60829b","order":2},{"adult":false,"gender":0,"id":3716703,"known_for_department":"Acting","name":"Ellie Cutbush","original_name":"Ellie Cutbush","popularity":0.0214,"profile_path":null,"cast_id":14,"character":"Tiffany","credit_id":"64a587688c44b900cab2a1b5","order":3},{"adult":false,"gender":0,"id":4148230,"known_for_department":"Acting","name":"Michael Surjan","original_name":"Michael Surjan","popularity":0.0239,"profile_path":null,"cast_id":15,"character":"Jason","credit_id":"64a587728c44b900ebe913c6","order":4},{"adult":false,"gender":0,"id":4148231,"known_for_department":"Acting","name":"Carrie McMahon","original_name":"Carrie McMahon","popularity":0.0143,"profile_path":null,"cast_id":16,"character":"Jasmine","credit_id":"64a5877ca0be28010df2500d","order":5}],"crew":[{"adult":false,"gender":0,"id":4567952,"known_for_department":"Directing","name":"Jules Burton","original_name":"Jules Burton","popularity":0.0732,"profile_path":null,"credit_id":"65e2da31e942be0187ea43dc","department":"Sound","job":"Music"},{"adult":false,"gender":0,"id":4567952,"known_for_department":"Directing","name":"Jules Burton","original_name":"Jules Burton","popularity":0.0732,"profile_path":null,"credit_id":"65e2d9fb278d8a0162bd9367","department":"Directing","job":"Director"},{"adult":false,"gender":0,"id":4148221,"known_for_department":"Crew","name":"Matthias Zver","original_name":"Matthias Zver","popularity":0.0071,"profile_path":null,"credit_id":"64a586f4a0be2800aed58d1c","department":"Crew","job":"Choreographer"},{"adult":false,"gender":0,"id":4148220,"known_for_department":"Sound","name":"Aidan Thomas","original_name":"Aidan Thomas","popularity":0.0071,"profile_path":null,"credit_id":"64a586e8da10f001397c7b51","department":"Sound","job":"Sound"},{"adult":false,"gender":0,"id":4148204,"known_for_department":"Production","name":"Jessica Canakis","original_name":"Jessica Canakis","popularity":0,"profile_path":null,"credit_id":"64a586698c44b9014e3ba8f8","department":"Production","job":"Producer"},{"adult":false,"gender":0,"id":3400078,"known_for_department":"Directing","name":"Dylan Randall","original_name":"Dylan Randall","popularity":0.0168,"profile_path":null,"credit_id":"64a58653158c8500e24ab73f","department":"Directing","job":"Director"},{"adult":false,"gender":0,"id":4148217,"known_for_department":"Directing","name":"Hunter Perry","original_name":"Hunter Perry","popularity":0.0261,"profile_path":null,"credit_id":"64a586db8c44b900ae608275","department":"Directing","job":"First Assistant Director"},{"adult":false,"gender":0,"id":4148211,"known_for_department":"Sound","name":"Chloe Lockyer","original_name":"Chloe Lockyer","popularity":0,"profile_path":null,"credit_id":"64a586941bf26600acaee868","department":"Sound","job":"Music"},{"adult":false,"gender":0,"id":3400078,"known_for_department":"Directing","name":"Dylan Randall","original_name":"Dylan Randall","popularity":0.0168,"profile_path":null,"credit_id":"64a586b55a991500adf87735","department":"Writing","job":"Writer"},{"adult":false,"gender":0,"id":4148215,"known_for_department":"Production","name":"Teaghan Lowry","original_name":"Teaghan Lowry","popularity":0,"profile_path":null,"credit_id":"64a586ca8c44b9012d6c2fa5","department":"Production","job":"Executive Producer"}]},"external_ids":{"imdb_id":"tt26083656","wikidata_id":null,"facebook_id":null,"instagram_id":null,"twitter_id":null},"images":{"backdrops":[{"aspect_ratio":1.778,"height":2160,"iso_639_1":null,"file_path":"/wyaBqurezQubtip2D7VfBFbsmtT.jpg","vote_average":0,"vote_count":0,"width":3840}],"logos":[],"posters":[{"aspect_ratio":0.667,"height":3000,"iso_639_1":"en","file_path":"/yk6eMTwSdSb4TKEUmEPF6xvfnKt.jpg","vote_average":3.334,"vote_count":1,"width":2000},{"aspect_ratio":0.675,"height":2963,"iso_639_1":"en","file_path":"/48G7m3rGuJWKa2WTLbyrAkyan57.jpg","vote_average":1.75,"vote_count":2,"width":2000}]},"keywords":{"keywords":[]},"release_dates":{"results":[{"iso_3166_1":"AU","release_dates":[{"certification":"","descriptors":[],"iso_639_1":"en","note":"","release_date":"2023-06-11T00:00:00.000Z","type":1}]}]},"videos":{"results":[{"iso_639_1":"en","iso_3166_1":"US","name":"SWEET RHYTHM | Official Trailer - Prudence Ackrill, Hannah Julii Anderson, Lainey O'Sullivan","key":"u8le7s4YkhE","site":"YouTube","size":1080,"type":"Trailer","official":false,"published_at":"2023-02-10T11:00:12.000Z","id":"64ca4b0add83fa00ff51852c"}]}}}