{"id":1402353,"retrievedAt":"2025-04-26T03:18:00.517Z","response":{"adult":false,"backdrop_path":null,"belongs_to_collection":null,"budget":0,"genres":[{"id":35,"name":"Comedy"},{"id":27,"name":"Horror"}],"homepage":"","id":1402353,"imdb_id":"tt20250048","origin_country":["ES"],"original_language":"es","original_title":"Pandemia Zombie","overview":"","popularity":0.0468,"poster_path":"/ArjGKI6Jj50PjpxctAyOu1x5dcG.jpg","production_companies":[],"production_countries":[{"iso_3166_1":"ES","name":"Spain"}],"release_date":"2022-05-17","revenue":0,"runtime":0,"spoken_languages":[{"english_name":"Spanish","iso_639_1":"es","name":"Español"}],"status":"Released","tagline":"","title":"Pandemia Zombie","video":false,"vote_average":0,"vote_count":0,"alternative_titles":{"titles":[{"iso_3166_1":"US","title":"Zombie Pandemic","type":""}]},"credits":{"cast":[{"adult":false,"gender":0,"id":5119653,"known_for_department":"Acting","name":"Albert Riballo","original_name":"Albert Riballo","popularity":0,"profile_path":null,"cast_id":1,"character":"","credit_id":"675e05e7d6f5e8458b8b2670","order":0},{"adult":false,"gender":2,"id":2198643,"known_for_department":"Acting","name":"Santi Bayón","original_name":"Santi Bayón","popularity":0.0839,"profile_path":"/myTk8IlwUsQph4BPMMn2ZiETnK.jpg","cast_id":2,"character":"","credit_id":"675e05f8de8f34e0b2586289","order":1}],"crew":[{"adult":false,"gender":2,"id":1346524,"known_for_department":"Directing","name":"Ignacio Rodó","original_name":"Ignacio Rodó","popularity":0.0806,"profile_path":"/2KERSdZ2MD3kxL5eLkrv9vpMEgZ.jpg","credit_id":"675e061fd6f5e8458b8b2687","department":"Directing","job":"Director"},{"adult":false,"gender":2,"id":1346524,"known_for_department":"Directing","name":"Ignacio Rodó","original_name":"Ignacio Rodó","popularity":0.0806,"profile_path":"/2KERSdZ2MD3kxL5eLkrv9vpMEgZ.jpg","credit_id":"675e064df988836160b01286","department":"Writing","job":"Writer"}]},"external_ids":{"imdb_id":"tt20250048","wikidata_id":null,"facebook_id":null,"instagram_id":null,"twitter_id":null},"images":{"backdrops":[],"logos":[],"posters":[{"aspect_ratio":0.667,"height":1800,"iso_639_1":null,"file_path":"/ArjGKI6Jj50PjpxctAyOu1x5dcG.jpg","vote_average":3.334,"vote_count":1,"width":1200}]},"keywords":{"keywords":[]},"release_dates":{"results":[{"iso_3166_1":"ES","release_dates":[{"certification":"Ai","descriptors":[],"iso_639_1":"es","note":"","release_date":"2022-05-17T00:00:00.000Z","type":4}]}]},"videos":{"results":[]}}}