{"id":1687290,"retrievedAt":"2026-05-04T12:41:12.296Z","response":{"adult":false,"backdrop_path":null,"belongs_to_collection":null,"budget":0,"genres":[{"id":10751,"name":"Family"},{"id":18,"name":"Drama"}],"homepage":"","id":1687290,"imdb_id":null,"origin_country":["US"],"original_language":"en","original_title":"Sikatayo","overview":"The story of Mark, a bright young man used to the unaffectionate character of his mother, Delia, his whole life. But as he finds her one day acting the exact opposite, Mark does everything he can to find out the reason behind her change of character.","popularity":0.0286,"poster_path":"/lNjK3ADznI7gM0MMAqe95lXahzP.jpg","production_companies":[],"production_countries":[],"release_date":"2025-12-16","revenue":0,"runtime":15,"softcore":false,"spoken_languages":[],"status":"Released","tagline":"","title":"Sikatayo","video":false,"vote_average":0,"vote_count":0,"credits":{"cast":[{"adult":false,"gender":0,"id":6186010,"known_for_department":"Acting","name":"Julian Morales","original_name":"Julian Morales","popularity":0,"profile_path":null,"cast_id":1,"character":"Mark","credit_id":"69f726b8727bd06e543a4afe","order":0},{"adult":false,"gender":0,"id":6186011,"known_for_department":"Acting","name":"Joanna Suarez","original_name":"Joanna Suarez","popularity":0,"profile_path":null,"cast_id":2,"character":"Delia","credit_id":"69f726c6727bd06e543a4b09","order":1}],"crew":[{"adult":false,"gender":0,"id":6186012,"known_for_department":"Writing","name":"Arieana Ayos","original_name":"Arieana Ayos","popularity":0,"profile_path":null,"credit_id":"69f726dbff31bb963238d882","department":"Directing","job":"Director"},{"adult":false,"gender":0,"id":6186012,"known_for_department":"Writing","name":"Arieana Ayos","original_name":"Arieana Ayos","popularity":0,"profile_path":null,"credit_id":"69f726e6f235581cfd3a4910","department":"Writing","job":"Writer"},{"adult":false,"gender":0,"id":6186013,"known_for_department":"Writing","name":"Cherry Alvarez","original_name":"Cherry Alvarez","popularity":0,"profile_path":null,"credit_id":"69f726f4f235581cfd3a491e","department":"Writing","job":"Writer"},{"adult":false,"gender":0,"id":5976217,"known_for_department":"Camera","name":"Aldriney Harris","original_name":"Aldriney Harris","popularity":0,"profile_path":null,"credit_id":"69f726ff74e4cdc16d5ec0bc","department":"Production","job":"Producer"},{"adult":false,"gender":0,"id":6186014,"known_for_department":"Camera","name":"Monty Unating","original_name":"Monty Unating","popularity":0,"profile_path":null,"credit_id":"69f7270bf95f5bf4063a4ae8","department":"Camera","job":"Director of Photography"},{"adult":false,"gender":0,"id":6186015,"known_for_department":"Directing","name":"Jiel Mae Tamondong","original_name":"Jiel Mae Tamondong","popularity":0,"profile_path":null,"credit_id":"69f7272544ab088dbf7d122f","department":"Directing","job":"Assistant Director"},{"adult":false,"gender":0,"id":6186016,"known_for_department":"Art","name":"Ryzel Kim Soriano","original_name":"Ryzel Kim Soriano","popularity":0,"profile_path":null,"credit_id":"69f72738b7828b063b5ec158","department":"Art","job":"Production Design"},{"adult":false,"gender":0,"id":6186017,"known_for_department":"Production","name":"Hannih Kirsten Dimatulac","original_name":"Hannih Kirsten Dimatulac","popularity":0,"profile_path":null,"credit_id":"69f72750970ddd4c93d57e51","department":"Production","job":"Production Manager"},{"adult":false,"gender":0,"id":5172437,"known_for_department":"Directing","name":"Erwin Garcia","original_name":"Erwin Garcia","popularity":0.0071,"profile_path":null,"credit_id":"69f7276f2f3100165cdb42b5","department":"Directing","job":"Script Supervisor"},{"adult":false,"gender":1,"id":5691890,"known_for_department":"Directing","name":"Niña Denise Garcia","original_name":"Niña Denise Garcia","popularity":0.0071,"profile_path":"/2VT1F8rS3CmAHDzjfMDuLLh1sw3.jpg","credit_id":"69f7278348b35418667d1228","department":"Sound","job":"Sound"},{"adult":false,"gender":0,"id":5981041,"known_for_department":"Art","name":"Andrea De Los Rios","original_name":"Andrea De Los Rios","popularity":0,"profile_path":null,"credit_id":"69f7279ac9cb61d24738d891","department":"Lighting","job":"Gaffer"},{"adult":false,"gender":0,"id":6186018,"known_for_department":"Production","name":"Krisha Anzano","original_name":"Krisha Anzano","popularity":0,"profile_path":null,"credit_id":"69f727a9acfe45b71d5ec23b","department":"Production","job":"Production Assistant"},{"adult":false,"gender":0,"id":6186019,"known_for_department":"Editing","name":"Jed Lorenz Magat","original_name":"Jed Lorenz Magat","popularity":0,"profile_path":null,"credit_id":"69f727b9d219d5be9838d748","department":"Editing","job":"Editor"},{"adult":false,"gender":0,"id":6186020,"known_for_department":"Editing","name":"Shaun Aslarona","original_name":"Shaun Aslarona","popularity":0,"profile_path":null,"credit_id":"69f727d95b2f35513c7d1388","department":"Editing","job":"Editor"}]},"alternative_titles":{"titles":[]},"external_ids":{"imdb_id":null,"wikidata_id":null,"facebook_id":null,"instagram_id":null,"twitter_id":null},"images":{"backdrops":[],"logos":[],"posters":[{"aspect_ratio":0.7,"height":2500,"iso_3166_1":"US","iso_639_1":"en","file_path":"/lNjK3ADznI7gM0MMAqe95lXahzP.jpg","vote_average":0,"vote_count":0,"width":1750}]},"keywords":{"keywords":[]},"release_dates":{"results":[{"iso_3166_1":"PH","release_dates":[{"certification":"","descriptors":[],"iso_639_1":"","note":"","release_date":"2025-12-16T00:00:00.000Z","type":4}]}]},"videos":{"results":[]}}}