{"id":1074378,"retrievedAt":"2025-04-26T01:24:58.885Z","response":{"adult":false,"backdrop_path":"/1WP9SeYu60fcpStDcSIPrUq31DP.jpg","belongs_to_collection":null,"budget":0,"genres":[{"id":18,"name":"Drama"},{"id":35,"name":"Comedy"}],"homepage":"","id":1074378,"imdb_id":null,"origin_country":["CA"],"original_language":"en","original_title":"Onions","overview":"Amidst lockdowns and toilet paper shortages, Jack lands a date. The only problem? Jack can't cut onions to save his life. Slicing his finger moments before his date arrives, Jack must endure the pain in a vain attempt to conceal his wound.","popularity":0.0577,"poster_path":"/yXRcbyrCA44ggnD2bSjlRHq5G5X.jpg","production_companies":[],"production_countries":[{"iso_3166_1":"CA","name":"Canada"}],"release_date":"2021-04-15","revenue":0,"runtime":6,"spoken_languages":[],"status":"Released","tagline":"He's not crying over the onions...","title":"Onions","video":false,"vote_average":10,"vote_count":1,"alternative_titles":{"titles":[]},"credits":{"cast":[{"adult":false,"gender":0,"id":3874351,"known_for_department":"Acting","name":"Andrew Martel","original_name":"Andrew Martel","popularity":0.0362,"profile_path":null,"cast_id":21,"character":"Jack","credit_id":"63c45bccaaec710087a9c6a3","order":0},{"adult":false,"gender":0,"id":3874352,"known_for_department":"Acting","name":"Kayla Ossachuk","original_name":"Kayla Ossachuk","popularity":0.0261,"profile_path":null,"cast_id":22,"character":"Kate","credit_id":"63c45be5871b3400b5e78736","order":1}],"crew":[{"adult":false,"gender":0,"id":3874332,"known_for_department":"Sound","name":"Chris Kenney","original_name":"Chris Kenney","popularity":0.0143,"profile_path":null,"credit_id":"63c45a4eae384300c8d38560","department":"Sound","job":"Boom Operator"},{"adult":false,"gender":0,"id":3874341,"known_for_department":"Production","name":"Xaviar Johnson","original_name":"Xaviar Johnson","popularity":0.0143,"profile_path":null,"credit_id":"63c45b11aaec7100f0fbd5be","department":"Production","job":"Production Manager"},{"adult":false,"gender":0,"id":3874342,"known_for_department":"Directing","name":"Xaviar Johnson","original_name":"Xaviar Johnson","popularity":0.0071,"profile_path":null,"credit_id":"63c45b2e85005d008a66e103","department":"Directing","job":"Assistant Director"},{"adult":false,"gender":0,"id":3874344,"known_for_department":"Art","name":"Livia Steeves","original_name":"Livia Steeves","popularity":0.0239,"profile_path":null,"credit_id":"63c45b3f85005d0082fb67bf","department":"Art","job":"Art Direction"},{"adult":false,"gender":0,"id":3874326,"known_for_department":"Production","name":"Craig Hudson","original_name":"Craig Hudson","popularity":0,"profile_path":null,"credit_id":"63c459cf0231f200b637cc1b","department":"Production","job":"Location Coordinator"},{"adult":false,"gender":0,"id":3874344,"known_for_department":"Art","name":"Livia Steeves","original_name":"Livia Steeves","popularity":0.0239,"profile_path":null,"credit_id":"63c45b67ce997a00ae3ee9dd","department":"Camera","job":"Assistant Camera"},{"adult":false,"gender":0,"id":3874324,"known_for_department":"Directing","name":"Zerach Kearney","original_name":"Zerach Kearney","popularity":0.0387,"profile_path":null,"credit_id":"63c459adce997a00ae3ee975","department":"Directing","job":"Director"},{"adult":false,"gender":0,"id":3874333,"known_for_department":"Sound","name":"Craig Hudson","original_name":"Craig Hudson","popularity":0.0071,"profile_path":null,"credit_id":"63c45a5fd7fbda00cb7ce92b","department":"Sound","job":"Sound Mixer"},{"adult":false,"gender":0,"id":3874328,"known_for_department":"Editing","name":"Andrew McCullough","original_name":"Andrew McCullough","popularity":0.0143,"profile_path":null,"credit_id":"63c45a06aaec7100f0fbd577","department":"Editing","job":"Editor"},{"adult":false,"gender":0,"id":3874328,"known_for_department":"Editing","name":"Andrew McCullough","original_name":"Andrew McCullough","popularity":0.0143,"profile_path":null,"credit_id":"63c45af2d7fbda008a295c53","department":"Art","job":"Art Department Manager"},{"adult":false,"gender":0,"id":3874345,"known_for_department":"Camera","name":"Ellie Bidgood","original_name":"Ellie Bidgood","popularity":0.0071,"profile_path":null,"credit_id":"63c45b54ae384300c8d3859d","department":"Camera","job":"Assistant Camera"},{"adult":false,"gender":0,"id":3874329,"known_for_department":"Editing","name":"Ellie Bidgood","original_name":"Ellie Bidgood","popularity":0.0261,"profile_path":null,"credit_id":"63c45a15d7fbda0082071308","department":"Editing","job":"Editor"},{"adult":false,"gender":0,"id":3874334,"known_for_department":"Lighting","name":"Zachary St. Onge","original_name":"Zachary St. Onge","popularity":0.0071,"profile_path":null,"credit_id":"63c45a850231f200b637cc4f","department":"Lighting","job":"Lighting Technician"},{"adult":false,"gender":0,"id":3874334,"known_for_department":"Lighting","name":"Zachary St. Onge","original_name":"Zachary St. Onge","popularity":0.0071,"profile_path":null,"credit_id":"63c45a9f0231f200b637cc5d","department":"Camera","job":"Grip"},{"adult":false,"gender":0,"id":3874338,"known_for_department":"Camera","name":"Armin Panjwani","original_name":"Armin Panjwani","popularity":0.0071,"profile_path":null,"credit_id":"63c45ac2d7fbda00cb7ce94b","department":"Camera","job":"Camera Operator"},{"adult":false,"gender":0,"id":3874329,"known_for_department":"Editing","name":"Ellie Bidgood","original_name":"Ellie Bidgood","popularity":0.0261,"profile_path":null,"credit_id":"63c45a29ae38430093036e36","department":"Production","job":"Casting"},{"adult":false,"gender":0,"id":3874326,"known_for_department":"Production","name":"Craig Hudson","original_name":"Craig Hudson","popularity":0,"profile_path":null,"credit_id":"63c45a3bd7fbda008a295c22","department":"Sound","job":"Sound Editor"},{"adult":false,"gender":0,"id":3869676,"known_for_department":"Production","name":"Tony Merzetti","original_name":"Tony Merzetti","popularity":0,"profile_path":null,"credit_id":"63c45b83ce997a0087479e44","department":"Production","job":"Executive Producer"},{"adult":false,"gender":0,"id":3874328,"known_for_department":"Editing","name":"Andrew McCullough","original_name":"Andrew McCullough","popularity":0.0143,"profile_path":null,"credit_id":"63c45ad5871b34007f036195","department":"Directing","job":"Continuity"},{"adult":false,"gender":0,"id":3874334,"known_for_department":"Lighting","name":"Zachary St. Onge","original_name":"Zachary St. Onge","popularity":0.0071,"profile_path":null,"credit_id":"63c45a90d7fbda00a058244e","department":"Lighting","job":"Gaffer"},{"adult":false,"gender":0,"id":3874342,"known_for_department":"Directing","name":"Xaviar Johnson","original_name":"Xaviar Johnson","popularity":0.0071,"profile_path":null,"credit_id":"63c598abc9054f00da8b3182","department":"Art","job":"Art Department Manager"}]},"external_ids":{"imdb_id":null,"wikidata_id":null,"facebook_id":null,"instagram_id":null,"twitter_id":null},"images":{"backdrops":[{"aspect_ratio":1.778,"height":2160,"iso_639_1":null,"file_path":"/1WP9SeYu60fcpStDcSIPrUq31DP.jpg","vote_average":0,"vote_count":0,"width":3840}],"logos":[],"posters":[{"aspect_ratio":0.667,"height":3000,"iso_639_1":"en","file_path":"/yXRcbyrCA44ggnD2bSjlRHq5G5X.jpg","vote_average":0,"vote_count":0,"width":2000}]},"keywords":{"keywords":[]},"release_dates":{"results":[{"iso_3166_1":"CA","release_dates":[{"certification":"PG","descriptors":["Violence"],"iso_639_1":"en","note":"","release_date":"2021-04-15T00:00:00.000Z","type":3}]}]},"videos":{"results":[]}}}