{"id":269073,"retrievedAt":"2025-04-25T20:38:46.733Z","response":{"adult":false,"backdrop_path":null,"belongs_to_collection":null,"budget":0,"genres":[{"id":18,"name":"Drama"}],"homepage":"","id":269073,"imdb_id":"tt0135064","origin_country":["FI"],"original_language":"fi","original_title":"Yksityisalue","overview":"An apparent suicide of a successful architect prompts an investigation into his death. A young man investigating can't believe that his well-respected boss would take his own life until he discovers that the man had a loveless marriage, another woman on the side, and a general feeling of malaise – a condition caused by the fact that he very nearly sold himself out to the lure of big money.","popularity":0.2255,"poster_path":"/3URMP5mRC6tztaFHsuebWmVQ0dl.jpg","production_companies":[{"id":106161,"logo_path":null,"name":"Kurkvaara-Filmi","origin_country":"FI"}],"production_countries":[{"iso_3166_1":"FI","name":"Finland"}],"release_date":"1962-10-05","revenue":0,"runtime":83,"spoken_languages":[{"english_name":"Finnish","iso_639_1":"fi","name":"suomi"}],"status":"Released","tagline":"","title":"Yksityisalue","video":false,"vote_average":5.7,"vote_count":3,"alternative_titles":{"titles":[]},"credits":{"cast":[{"adult":false,"gender":2,"id":931477,"known_for_department":"Acting","name":"Kalervo Nissilä","original_name":"Kalervo Nissilä","popularity":0.0761,"profile_path":"/gIwVTmFXlteyVlbxPq7mGjVs9aB.jpg","cast_id":5,"character":"Toivo Koski","credit_id":"6416c9d2e74146008216a4e9","order":0},{"adult":false,"gender":1,"id":1364544,"known_for_department":"Acting","name":"Kyllikki Forssell","original_name":"Kyllikki Forssell","popularity":0.0505,"profile_path":null,"cast_id":3,"character":"Margit Koski","credit_id":"54182dfcc3a368199f002e73","order":1},{"adult":false,"gender":2,"id":1592185,"known_for_department":"Acting","name":"Jarno Hiilloskorpi","original_name":"Jarno Hiilloskorpi","popularity":0.0193,"profile_path":"/obZsXswbeCUHZYrnCFhDlQ7SM9z.jpg","cast_id":6,"character":"Pentti Vaara","credit_id":"6416ca0831032500e8a21e1f","order":2},{"adult":false,"gender":1,"id":1364543,"known_for_department":"Acting","name":"Sinikka Hannula","original_name":"Sinikka Hannula","popularity":0.1342,"profile_path":null,"cast_id":2,"character":"Kaisu","credit_id":"54182df10e0a263804002d10","order":3},{"adult":false,"gender":2,"id":110766,"known_for_department":"Acting","name":"Pehr-Olof Sirén","original_name":"Pehr-Olof Sirén","popularity":0.1508,"profile_path":"/eRrfiH3DgwA4ICbzCdBKkdyTA4V.jpg","cast_id":7,"character":"Mäkelä","credit_id":"6416ca32e9c0dc008f713078","order":4},{"adult":false,"gender":1,"id":1364542,"known_for_department":"Acting","name":"Sointu Angervo","original_name":"Sointu Angervo","popularity":0.0362,"profile_path":null,"cast_id":1,"character":"Soili","credit_id":"54182de50e0a26380b002e37","order":5},{"adult":false,"gender":2,"id":1303607,"known_for_department":"Acting","name":"Kaarlo Halttunen","original_name":"Kaarlo Halttunen","popularity":0.0674,"profile_path":"/s7D0auoz22dlvVtL1ez90D36wgv.jpg","cast_id":8,"character":"Dr. Carlstedt","credit_id":"6416ca8ce74146008671cbf9","order":6},{"adult":false,"gender":2,"id":1205464,"known_for_department":"Acting","name":"Sasu Haapanen","original_name":"Sasu Haapanen","popularity":0.0793,"profile_path":"/b3rKE8L6hmRAQ22cd3M2DBgA5rd.jpg","cast_id":9,"character":"","credit_id":"6416ca98310325008efcf7e5","order":7},{"adult":false,"gender":2,"id":1982844,"known_for_department":"Acting","name":"Esko Mannermaa","original_name":"Esko Mannermaa","popularity":0.0802,"profile_path":null,"cast_id":10,"character":"Salin","credit_id":"6416caaf310325008efcf7ee","order":8},{"adult":false,"gender":2,"id":2690803,"known_for_department":"Acting","name":"Aimo Tepponen","original_name":"Aimo Tepponen","popularity":0.0256,"profile_path":null,"cast_id":11,"character":"","credit_id":"6416cabf5690b500d4012fe3","order":9},{"adult":false,"gender":2,"id":1166132,"known_for_department":"Acting","name":"Tauno Söder","original_name":"Tauno Söder","popularity":0.0362,"profile_path":null,"cast_id":12,"character":"Rape Sollman","credit_id":"6416cad66a2227007d7316ab","order":10},{"adult":false,"gender":2,"id":114143,"known_for_department":"Acting","name":"Nils Brandt","original_name":"Nils Brandt","popularity":0.1766,"profile_path":"/1IO5PCSfLc3j1SSYTbSncLvZbA0.jpg","cast_id":4,"character":"","credit_id":"54182e140e0a2637f9002e2e","order":11},{"adult":false,"gender":1,"id":3968953,"known_for_department":"Acting","name":"Mirja Lehtinen","original_name":"Mirja Lehtinen","popularity":0.0218,"profile_path":null,"cast_id":13,"character":"Kipa","credit_id":"6416cb2031032500c5a9e2d9","order":12},{"adult":false,"gender":1,"id":2140862,"known_for_department":"Directing","name":"Sirpa Silventoinen","original_name":"Sirpa Silventoinen","popularity":0.0214,"profile_path":null,"cast_id":14,"character":"Pirkko","credit_id":"6416cb335690b5007a54bb5b","order":13}],"crew":[{"adult":false,"gender":2,"id":1364541,"known_for_department":"Directing","name":"Maunu Kurkvaara","original_name":"Maunu Kurkvaara","popularity":0.0641,"profile_path":"/zFeFzU5d10XPmmgDEXPRt0DpJI1.jpg","credit_id":"54182ddcc3a36819a8002def","department":"Directing","job":"Director"},{"adult":false,"gender":2,"id":1364541,"known_for_department":"Directing","name":"Maunu Kurkvaara","original_name":"Maunu Kurkvaara","popularity":0.0641,"profile_path":"/zFeFzU5d10XPmmgDEXPRt0DpJI1.jpg","credit_id":"6416cbfde74146008671cc9f","department":"Writing","job":"Writer"},{"adult":false,"gender":2,"id":3099256,"known_for_department":"Sound","name":"Usko Meriläinen","original_name":"Usko Meriläinen","popularity":0.0416,"profile_path":null,"credit_id":"6416ccb0e9c0dc007b99b3be","department":"Sound","job":"Original Music Composer"},{"adult":false,"gender":2,"id":1364541,"known_for_department":"Directing","name":"Maunu Kurkvaara","original_name":"Maunu Kurkvaara","popularity":0.0641,"profile_path":"/zFeFzU5d10XPmmgDEXPRt0DpJI1.jpg","credit_id":"6416cd07e9c0dc00c3bded53","department":"Production","job":"Producer"},{"adult":false,"gender":2,"id":1674071,"known_for_department":"Sound","name":"Tuomo Kattilakoski","original_name":"Tuomo Kattilakoski","popularity":0.1077,"profile_path":null,"credit_id":"6416cc60e74146007c822688","department":"Sound","job":"Production Sound Mixer"},{"adult":false,"gender":2,"id":1364541,"known_for_department":"Directing","name":"Maunu Kurkvaara","original_name":"Maunu Kurkvaara","popularity":0.0641,"profile_path":"/zFeFzU5d10XPmmgDEXPRt0DpJI1.jpg","credit_id":"6416cc0d6a222700e975992f","department":"Camera","job":"Director of Photography"}]},"external_ids":{"imdb_id":"tt0135064","wikidata_id":"Q8053987","facebook_id":null,"instagram_id":null,"twitter_id":null},"images":{"backdrops":[],"logos":[],"posters":[{"aspect_ratio":0.679,"height":1000,"iso_639_1":"fi","file_path":"/3URMP5mRC6tztaFHsuebWmVQ0dl.jpg","vote_average":0,"vote_count":0,"width":679}]},"keywords":{"keywords":[]},"release_dates":{"results":[{"iso_3166_1":"FI","release_dates":[{"certification":"K-16","descriptors":[],"iso_639_1":"","note":"","release_date":"1962-10-05T00:00:00.000Z","type":3}]}]},"videos":{"results":[]}}}