{"id":1530784,"retrievedAt":"2025-08-16T11:32:16.422Z","response":{"adult":true,"backdrop_path":null,"belongs_to_collection":null,"budget":0,"genres":[],"homepage":"","id":1530784,"imdb_id":null,"origin_country":["US"],"original_language":"en","original_title":"Teen Extreme Deepthroat","overview":"Barely legal teens cant wait to strip off their clothes off and prove that they know all kinds of sexual pleasures. These sluts begin by giving big cocks a handjob followed by a nasty blowjob before they get a good pounding. Turned on, horny men load off their refreshing cum into their filthy waiting mouths.","popularity":0,"poster_path":"/6ahYw17eD1PwFLv8iIsUIu5Kl03.jpg","production_companies":[{"id":198792,"logo_path":null,"name":"Cream Loving Teens","origin_country":""}],"production_countries":[{"iso_3166_1":"US","name":"United States of America"}],"release_date":"2020-01-01","revenue":0,"runtime":77,"spoken_languages":[{"english_name":"Russian","iso_639_1":"ru","name":"Pусский"}],"status":"Released","tagline":"","title":"Teen Extreme Deepthroat","video":true,"vote_average":7,"vote_count":1,"alternative_titles":{"titles":[]},"credits":{"cast":[{"adult":true,"gender":1,"id":1969146,"known_for_department":"Acting","name":"Amelie Pure","original_name":"Amelie Pure","popularity":0.6,"profile_path":"/oXvNNeR5dhDhQwy4UTYZQqCbSqh.jpg","cast_id":1,"character":"(as Devon) (archive footage)","credit_id":"689ffb10131fb0669f855fe9","order":0},{"adult":true,"gender":1,"id":2171100,"known_for_department":"Acting","name":"Katy","original_name":"Katy","popularity":0.6,"profile_path":"/dpoF43yYIrae8cb3sb9MnGdq7jG.jpg","cast_id":2,"character":"(as Mia) (archive footage)","credit_id":"689ffb20739fb0903b856032","order":1},{"adult":true,"gender":1,"id":2914805,"known_for_department":"Acting","name":"Spice","original_name":"Spice","popularity":0.6,"profile_path":"/nAMNECbK71BIyeJjC74ZbWZF387.jpg","cast_id":3,"character":"(as Virginee) (archive footage)","credit_id":"689ffb32d2a576afe8855fac","order":2},{"adult":true,"gender":2,"id":2386926,"known_for_department":"Acting","name":"Kich","original_name":"Kich","popularity":0.6,"profile_path":"/kiUUShGsEdpBerCHFLaEchYNpd2.jpg","cast_id":4,"character":"(archive footage)","credit_id":"689ffb3a825984522d855fde","order":3},{"adult":true,"gender":2,"id":2926388,"known_for_department":"Acting","name":"Stas","original_name":"Stas","popularity":0.6,"profile_path":"/ewhA6PnLO0trTs6Eca61IrQb8vB.jpg","cast_id":5,"character":"(archive footage)","credit_id":"689ffb4121e1b61043855fab","order":4},{"adult":true,"gender":2,"id":1771424,"known_for_department":"Acting","name":"Yuriy Sergeev","original_name":"Yuriy Sergeev","popularity":4.708,"profile_path":"/AfqMEr72aiQNZhcBk1v6daDeYB2.jpg","cast_id":6,"character":"(archive footage)","credit_id":"689ffb49da58d52aecec73de","order":5}],"crew":[]},"external_ids":{"imdb_id":null,"wikidata_id":null,"facebook_id":null,"instagram_id":null,"twitter_id":null},"images":{"backdrops":[],"logos":[],"posters":[{"aspect_ratio":0.667,"height":750,"iso_639_1":"en","file_path":"/6ahYw17eD1PwFLv8iIsUIu5Kl03.jpg","vote_average":0,"vote_count":0,"width":500}]},"keywords":{"keywords":[{"id":12197,"name":"compilation"},{"id":331279,"name":"russian girls"},{"id":346617,"name":"teen"}]},"release_dates":{"results":[{"iso_3166_1":"US","release_dates":[{"certification":"NC-17","descriptors":[],"iso_639_1":"","note":"","release_date":"2020-01-01T00:00:00.000Z","type":5}]}]},"videos":{"results":[]}}}