{"id":823925,"retrievedAt":"2025-04-26T00:04:13.072Z","response":{"adult":false,"backdrop_path":null,"belongs_to_collection":null,"budget":19480,"genres":[{"id":35,"name":"Comedy"}],"homepage":"https://www.youtube.com/watch?time_continue=152&v=KXgygshwkK4&feature=emb_title","id":823925,"imdb_id":"tt4625388","origin_country":["US"],"original_language":"en","original_title":"The Peeps vs. Buddytron","overview":"Set in a dystopian not-too-distant future, this anarchic half-hour sitcom/sketch show follows a cast of crazed characters who are drawn together by a nefarious social networking site called Buddytron.","popularity":0.1616,"poster_path":"/6ZvqQrxcCpisrXerbUtADrQvX7B.jpg","production_companies":[],"production_countries":[],"release_date":"2008-11-10","revenue":0,"runtime":28,"spoken_languages":[],"status":"Released","tagline":"","title":"The Peeps vs. Buddytron","video":false,"vote_average":0,"vote_count":0,"alternative_titles":{"titles":[]},"credits":{"cast":[{"adult":false,"gender":2,"id":1539586,"known_for_department":"Writing","name":"Nikos Andronicos","original_name":"Nikos Andronicos","popularity":0.0256,"profile_path":"/51YWje8zVwE9Di7sQgVonden2cc.jpg","cast_id":1,"character":"Billy Custard","credit_id":"608a501a43250f005728eacb","order":0},{"adult":false,"gender":2,"id":1217765,"known_for_department":"Acting","name":"James McFay","original_name":"James McFay","popularity":0.2576,"profile_path":"/7CC5blDvn1tRoVoVW0ZPASepf23.jpg","cast_id":2,"character":"Zooky Jones","credit_id":"608a504a66469a00716d637d","order":1},{"adult":false,"gender":0,"id":1539585,"known_for_department":"Acting","name":"Andrew Johnston","original_name":"Andrew Johnston","popularity":0.0261,"profile_path":null,"cast_id":3,"character":"Quaychow Lim","credit_id":"608a50d39463180042a6a681","order":2},{"adult":false,"gender":0,"id":3071688,"known_for_department":"Acting","name":"Anthony Levin","original_name":"Anthony Levin","popularity":0.0071,"profile_path":null,"cast_id":4,"character":"Van Borg","credit_id":"608a51175b2f470079812553","order":3},{"adult":false,"gender":0,"id":3071690,"known_for_department":"Acting","name":"Dom Fitzgerald","original_name":"Dom Fitzgerald","popularity":0.0214,"profile_path":null,"cast_id":5,"character":"Boss Hung","credit_id":"608a512f481382007aec5a63","order":4},{"adult":false,"gender":0,"id":3071691,"known_for_department":"Acting","name":"Damien Timms","original_name":"Damien Timms","popularity":0,"profile_path":null,"cast_id":6,"character":"Gertie","credit_id":"608a515b258823007858e26f","order":5}],"crew":[{"adult":false,"gender":2,"id":1217765,"known_for_department":"Acting","name":"James McFay","original_name":"James McFay","popularity":0.2576,"profile_path":"/7CC5blDvn1tRoVoVW0ZPASepf23.jpg","credit_id":"608a51f443250f00296f3440","department":"Editing","job":"Editor"},{"adult":false,"gender":0,"id":1539585,"known_for_department":"Acting","name":"Andrew Johnston","original_name":"Andrew Johnston","popularity":0.0261,"profile_path":null,"credit_id":"608a5224a217c0005801424d","department":"Writing","job":"Writer"},{"adult":false,"gender":0,"id":3071688,"known_for_department":"Acting","name":"Anthony Levin","original_name":"Anthony Levin","popularity":0.0071,"profile_path":null,"credit_id":"608a52345b2f47002a3c30e9","department":"Writing","job":"Writer"},{"adult":false,"gender":2,"id":1539586,"known_for_department":"Writing","name":"Nikos Andronicos","original_name":"Nikos Andronicos","popularity":0.0256,"profile_path":"/51YWje8zVwE9Di7sQgVonden2cc.jpg","credit_id":"608a51abf8aee80040b42343","department":"Editing","job":"Editor"},{"adult":false,"gender":2,"id":1217765,"known_for_department":"Acting","name":"James McFay","original_name":"James McFay","popularity":0.2576,"profile_path":"/7CC5blDvn1tRoVoVW0ZPASepf23.jpg","credit_id":"608a51cc0835470078ecc51b","department":"Writing","job":"Writer"},{"adult":false,"gender":2,"id":1539586,"known_for_department":"Writing","name":"Nikos Andronicos","original_name":"Nikos Andronicos","popularity":0.0256,"profile_path":"/51YWje8zVwE9Di7sQgVonden2cc.jpg","credit_id":"608a517d38520200788f4f61","department":"Writing","job":"Writer"},{"adult":false,"gender":2,"id":1539586,"known_for_department":"Writing","name":"Nikos Andronicos","original_name":"Nikos Andronicos","popularity":0.0256,"profile_path":"/51YWje8zVwE9Di7sQgVonden2cc.jpg","credit_id":"608a519b43250f005728ebde","department":"Sound","job":"Music"},{"adult":false,"gender":2,"id":1217765,"known_for_department":"Acting","name":"James McFay","original_name":"James McFay","popularity":0.2576,"profile_path":"/7CC5blDvn1tRoVoVW0ZPASepf23.jpg","credit_id":"608a51eb258823002690977b","department":"Sound","job":"Music"},{"adult":false,"gender":0,"id":3071690,"known_for_department":"Acting","name":"Dom Fitzgerald","original_name":"Dom Fitzgerald","popularity":0.0214,"profile_path":null,"credit_id":"608a52112dc44e0040b0fab4","department":"Writing","job":"Writer"},{"adult":false,"gender":0,"id":1271977,"known_for_department":"Camera","name":"Simon Riera","original_name":"Simon Riera","popularity":0.0486,"profile_path":null,"credit_id":"608a52737b7b4d0029583e21","department":"Camera","job":"Director of Photography"},{"adult":false,"gender":2,"id":1539586,"known_for_department":"Writing","name":"Nikos Andronicos","original_name":"Nikos Andronicos","popularity":0.0256,"profile_path":"/51YWje8zVwE9Di7sQgVonden2cc.jpg","credit_id":"608a518e5b2f470079812567","department":"Production","job":"Producer"},{"adult":false,"gender":2,"id":1539586,"known_for_department":"Writing","name":"Nikos Andronicos","original_name":"Nikos Andronicos","popularity":0.0256,"profile_path":"/51YWje8zVwE9Di7sQgVonden2cc.jpg","credit_id":"608a517545765d00402e3509","department":"Directing","job":"Director"},{"adult":false,"gender":0,"id":3071691,"known_for_department":"Acting","name":"Damien Timms","original_name":"Damien Timms","popularity":0,"profile_path":null,"credit_id":"608a524243250f00776b81f2","department":"Writing","job":"Writer"},{"adult":false,"gender":2,"id":1217765,"known_for_department":"Acting","name":"James McFay","original_name":"James McFay","popularity":0.2576,"profile_path":"/7CC5blDvn1tRoVoVW0ZPASepf23.jpg","credit_id":"608a51c37b7b4d003f8720b3","department":"Directing","job":"Director"},{"adult":false,"gender":0,"id":2214836,"known_for_department":"Production","name":"Lachlan Imrie","original_name":"Lachlan Imrie","popularity":0.0071,"profile_path":null,"credit_id":"608a525b9463180042a6a7ca","department":"Production","job":"Producer"},{"adult":false,"gender":2,"id":1217765,"known_for_department":"Acting","name":"James McFay","original_name":"James McFay","popularity":0.2576,"profile_path":"/7CC5blDvn1tRoVoVW0ZPASepf23.jpg","credit_id":"608a51db08354700402dbf16","department":"Production","job":"Producer"}]},"external_ids":{"imdb_id":"tt4625388","wikidata_id":null,"facebook_id":null,"instagram_id":null,"twitter_id":null},"images":{"backdrops":[],"logos":[],"posters":[{"aspect_ratio":0.667,"height":1443,"iso_639_1":null,"file_path":"/6ZvqQrxcCpisrXerbUtADrQvX7B.jpg","vote_average":0,"vote_count":0,"width":962}]},"keywords":{"keywords":[]},"release_dates":{"results":[{"iso_3166_1":"AU","release_dates":[{"certification":"","descriptors":[],"iso_639_1":"en","note":"","release_date":"2008-11-10T00:00:00.000Z","type":6}]}]},"videos":{"results":[{"iso_639_1":"en","iso_3166_1":"US","name":"The Peeps vs Buddytron - Trailer by The Nice Guys","key":"KXgygshwkK4","site":"YouTube","size":480,"type":"Trailer","official":false,"published_at":"2015-04-05T00:43:00.000Z","id":"608a52e21d1bf40029d07c4b"}]}}}